{"v":4,"entries":{"spaghetti-button--docs":{"id":"spaghetti-button--docs","title":"Spaghetti/Button","name":"Docs","importPath":"./src/stories/components/Button.stories.ts","type":"docs","tags":["autodocs","docs"],"storiesImports":[]},"spaghetti-button--primary":{"type":"story","id":"spaghetti-button--primary","name":"Primary","title":"Spaghetti/Button","importPath":"./src/stories/components/Button.stories.ts","tags":["autodocs","story"]},"spaghetti-button--secondary":{"type":"story","id":"spaghetti-button--secondary","name":"Secondary","title":"Spaghetti/Button","importPath":"./src/stories/components/Button.stories.ts","tags":["autodocs","story"]},"spaghetti-button--positive":{"type":"story","id":"spaghetti-button--positive","name":"Positive","title":"Spaghetti/Button","importPath":"./src/stories/components/Button.stories.ts","tags":["autodocs","story"]},"spaghetti-button--outline":{"type":"story","id":"spaghetti-button--outline","name":"Outline","title":"Spaghetti/Button","importPath":"./src/stories/components/Button.stories.ts","tags":["autodocs","story"]},"spaghetti-button--with-suffix-icon":{"type":"story","id":"spaghetti-button--with-suffix-icon","name":"With Suffix Icon","title":"Spaghetti/Button","importPath":"./src/stories/components/Button.stories.ts","tags":["autodocs","story"]},"spaghetti-button--with-prefix-icon":{"type":"story","id":"spaghetti-button--with-prefix-icon","name":"With Prefix Icon","title":"Spaghetti/Button","importPath":"./src/stories/components/Button.stories.ts","tags":["autodocs","story"]},"spaghetti-icon--docs":{"id":"spaghetti-icon--docs","title":"Spaghetti/Icon","name":"Docs","importPath":"./src/stories/components/Icon.stories.ts","type":"docs","tags":["autodocs","docs"],"storiesImports":[]},"spaghetti-icon--arrow-right":{"type":"story","id":"spaghetti-icon--arrow-right","name":"Arrow Right","title":"Spaghetti/Icon","importPath":"./src/stories/components/Icon.stories.ts","tags":["autodocs","story"]}}}
